docstring_generator/__init__.py
docstring_generator/__main__.py
docstring_generator/config.py
docstring_generator/docstring_generator.py
docstring_generator/docstring_writer.py
docstring_generator/extensions.py
docstring_generator/file_processor.py
docstring_generator/helpers.py
docstring_generator/templates.py
oryks_docstring_generator-0.5.0.dist-info/LICENSE
oryks_docstring_generator-0.5.0.dist-info/METADATA
oryks_docstring_generator-0.5.0.dist-info/WHEEL
oryks_docstring_generator-0.5.0.dist-info/top_level.txt
oryks_docstring_generator-0.5.0.dist-info/RECORD
