Metadata-Version: 2.1
Name: oryks-docstring-generator
Version: 0.5.0
Summary: A python library for generating documentation for python projects.
Home-page: https://youtube-wrapper.readthedocs.io/en/latest/index.html
Author: Lyle Okoth
Author-email: lyceokoth@gmail.com
License: MIT
Keywords: dosctrings,documentation
Platform: UNKNOWN
Classifier: Intended Audience :: Developers
Classifier: License :: OSI Approved :: MIT License
Classifier: Programming Language :: Python
Classifier: Programming Language :: Python :: 3
Classifier: Programming Language :: Python :: 3.11
Classifier: Programming Language :: Python :: 3.12
Classifier: Operating System :: OS Independent
License-File: LICENSE
Requires-Dist: black
Requires-Dist: langchain
Requires-Dist: langchain-openai
Requires-Dist: pydantic
Requires-Dist: pydantic-settings
